{"cameraMode":{"drawMode":0,"name":"Shaded","section":"Shading Mode"},"sceneLighting":false,"audioPlay":false,"sceneViewState":{"m_AlwaysRefresh":false,"showFog":true,"showSkybox":false,"showFlares":true,"showImageEffects":true,"showParticleSystems":true,"showVisualEffectGraphs":true,"m_FxEnabled":true},"in2DMode":false,"pivot":{"x":7.17924690246582,"y":3.501404285430908,"z":11.29082202911377},"rotation":{"x":0.05476865917444229,"y":-0.9446706175804138,"z":0.2111455202102661,"w":0.24503767490386964},"size":1.531480073928833,"orthographic":true}